PyNewWrite/PyNewWrite_activate.py
PyNewWrite/__init__.py
PyNewWrite/main.py
PyNewWrite/data/colors/colors.py
PyNewWrite/data/efects/efects.py
pynewwrite-0.2.1.dist-info/licenses/LICENSE
pynewwrite-0.2.1.dist-info/METADATA
pynewwrite-0.2.1.dist-info/WHEEL
pynewwrite-0.2.1.dist-info/top_level.txt
pynewwrite-0.2.1.dist-info/RECORD
