Metadata-Version: 2.4
Name: PyNewWrite
Version: 0.2.1
Summary: Новый спопоб вывода кода в Python
Home-page: https://github.com/EvgenEvkal
Author: Sigard_Vinter
Author-email: developer.vinter@gmail.com
Project-URL: Documentation, https://github.com/EvgenEvkal
Keywords: example python
Classifier: Programming Language :: Python :: 3.13
Classifier: License :: OSI Approved :: MIT License
Classifier: Operating System :: OS Independent
Requires-Python: >=3.7
License-File: LICENSE
Requires-Dist: requests>=2.25.1
Dynamic: author
Dynamic: author-email
Dynamic: classifier
Dynamic: description
Dynamic: description-content-type
Dynamic: home-page
Dynamic: keywords
Dynamic: license-file
Dynamic: project-url
Dynamic: requires-dist
Dynamic: requires-python
Dynamic: summary
